{"directed": false, "graph": [], "nodes": [{"y": "4175.044", "x": "588.85406", "id": "344"}, {"y": "4860.0", "x": "870.0", "id": "0"}, {"y": "9331.515", "x": "1397.7334", "id": "346"}, {"y": "1928.5481", "x": "933.66345", "id": "347"}, {"y": "6633.6113", "x": "1936.7616", "id": "340"}, {"y": "4261.9844", "x": "465.03638", "id": "341"}, {"y": "262.17273", "x": "406.98694", "id": "342"}, {"y": "3546.6355", "x": "313.3643", "id": "343"}, {"y": "5606.399", "x": "1359.3627", "id": "348"}, {"y": "4018.0615", "x": "700.9239", "id": "349"}, {"y": "7191.647", "x": "1309.3624", "id": "298"}, {"y": "5750.0", "x": "1260.0", "id": "299"}, {"y": "5114.9746", "x": "935.6763", "id": "296"}, {"y": "9123.398", "x": "1612.7512", "id": "297"}, {"y": "9060.0", "x": "1370.0", "id": "294"}, {"y": "6694.63", "x": "1879.3152", "id": "295"}, {"y": "3934.2986", "x": "498.9102", "id": "292"}, {"y": "5658.7036", "x": "1320.7567", "id": "293"}, {"y": "800.0", "x": "240.0", "id": "290"}, {"y": "6202.0166", "x": "1361.8533", "id": "291"}, {"y": "6308.0327", "x": "1913.5984", "id": "199"}, {"y": "5563.9233", "x": "1426.04", "id": "198"}, {"y": "8346.773", "x": "1505.7759", "id": "195"}, {"y": "4763.944", "x": "1419.0004", "id": "194"}, {"y": "3893.2024", "x": "956.1764", "id": "197"}, {"y": "5930.2236", "x": "1617.7086", "id": "196"}, {"y": "6514.452", "x": "1836.1205", "id": "191"}, {"y": "9820.0", "x": "1670.0", "id": "190"}, {"y": "6382.2793", "x": "1844.8231", "id": "193"}, {"y": "8580.0", "x": "1460.0", "id": "192"}, {"y": "5172.907", "x": "1354.4279", "id": "270"}, {"y": "9172.715", "x": "1664.5228", "id": "271"}, {"y": "3126.6355", "x": "1313.3641", "id": "272"}, {"y": "6653.1123", "x": "1766.8599", "id": "273"}, {"y": "4168.239", "x": "754.3102", "id": "274"}, {"y": "5594.536", "x": "1885.2212", "id": "275"}, {"y": "5652.1235", "x": "1710.9879", "id": "276"}, {"y": "5869.741", "x": "2016.4758", "id": "277"}, {"y": "3852.4463", "x": "462.75906", "id": "278"}, {"y": "2280.0", "x": "630.0", "id": "279"}, {"y": "6385.3965", "x": "1924.368", "id": "108"}, {"y": "1470.0", "x": "600.0", "id": "109"}, {"y": "6462.052", "x": "1337.6484", "id": "102"}, {"y": "5775.245", "x": "1900.4775", "id": "103"}, {"y": "6445.795", "x": "1643.1542", "id": "100"}, {"y": "4969.6416", "x": "1713.661", "id": "101"}, {"y": "3780.4685", "x": "754.5678", "id": "106"}, {"y": "3961.152", "x": "751.223", "id": "107"}, {"y": "5630.707", "x": "1237.4598", "id": "104"}, {"y": "6053.1636", "x": "1976.7435", "id": "105"}, {"y": "4150.626", "x": "498.86713", "id": "39"}, {"y": "10009.533", "x": "1715.0007", "id": "38"}, {"y": "1240.0", "x": "610.0", "id": "33"}, {"y": "4060.0", "x": "1120.0", "id": "32"}, {"y": "6821.435", "x": "1463.5946", "id": "31"}, {"y": "3891.6516", "x": "566.2228", "id": "30"}, {"y": "2170.0", "x": "700.0", "id": "37"}, {"y": "4040.1897", "x": "937.96497", "id": "36"}, {"y": "7780.0", "x": "1512.6001", "id": "35"}, {"y": "2890.0", "x": "810.0", "id": "34"}, {"y": "5034.0234", "x": "848.00775", "id": "339"}, {"y": "5772.74", "x": "1537.6224", "id": "338"}, {"y": "6426.318", "x": "1142.3447", "id": "335"}, {"y": "6358.619", "x": "1360.3899", "id": "334"}, {"y": "9420.0", "x": "1570.0", "id": "337"}, {"y": "9193.886", "x": "1602.726", "id": "336"}, {"y": "2313.3738", "x": "547.71106", "id": "331"}, {"y": "5500.0", "x": "1880.0", "id": "330"}, {"y": "963.8035", "x": "338.56335", "id": "333"}, {"y": "6277.6396", "x": "1318.9868", "id": "332"}, {"y": "6573.257", "x": "1971.4142", "id": "345"}, {"y": "3228.7305", "x": "677.46045", "id": "6"}, {"y": "3798.1335", "x": "1047.0582", "id": "99"}, {"y": "4373.593", "x": "565.26697", "id": "98"}, {"y": "6613.1646", "x": "1866.5134", "id": "91"}, {"y": "5029.3", "x": "1410.0", "id": "90"}, {"y": "3932.728", "x": "650.41327", "id": "93"}, {"y": "2060.0", "x": "530.0", "id": "92"}, {"y": "6595.6743", "x": "1208.4594", "id": "95"}, {"y": "5924.6143", "x": "1416.6979", "id": "94"}, {"y": "4196.2676", "x": "440.6923", "id": "97"}, {"y": "5419.7285", "x": "1109.7281", "id": "96"}, {"y": "3414.1904", "x": "1332.7379", "id": "238"}, {"y": "7390.0", "x": "1430.0", "id": "239"}, {"y": "5000.0", "x": "1170.0", "id": "234"}, {"y": "6010.7324", "x": "1607.8243", "id": "235"}, {"y": "6705.386", "x": "1377.1195", "id": "236"}, {"y": "1906.5167", "x": "534.7866", "id": "237"}, {"y": "6018.6353", "x": "1885.9769", "id": "230"}, {"y": "1950.0", "x": "840.0", "id": "231"}, {"y": "8786.401", "x": "1472.3558", "id": "232"}, {"y": "3907.7334", "x": "1269.4784", "id": "233"}, {"y": "4072.6873", "x": "509.1044", "id": "1"}, {"y": "4890.481", "x": "1535.3647", "id": "146"}, {"y": "5128.616", "x": "1234.6234", "id": "147"}, {"y": "4221.489", "x": "529.08264", "id": "144"}, {"y": "2200.0", "x": "770.0", "id": "145"}, {"y": "3940.389", "x": "974.2234", "id": "142"}, {"y": "6491.1416", "x": "1982.832", "id": "143"}, {"y": "6120.0", "x": "1430.0", "id": "140"}, {"y": "3728.5164", "x": "794.94434", "id": "141"}, {"y": "2850.0", "x": "920.0", "id": "148"}, {"y": "8353.658", "x": "1419.7406", "id": "149"}, {"y": "5954.4546", "x": "1504.4547", "id": "133"}, {"y": "3519.7285", "x": "789.7283", "id": "132"}, {"y": "8311.871", "x": "1563.911", "id": "131"}, {"y": "4062.5854", "x": "837.0774", "id": "130"}, {"y": "3466.6355", "x": "736.6357", "id": "137"}, {"y": "9920.0", "x": "1670.0", "id": "136"}, {"y": "6755.1675", "x": "1261.3816", "id": "135"}, {"y": "2438.173", "x": "609.2014", "id": "134"}, {"y": "4882.416", "x": "1319.474", "id": "139"}, {"y": "4301.6533", "x": "761.5302", "id": "138"}, {"y": "6740.0", "x": "1570.0", "id": "24"}, {"y": "1760.0", "x": "560.0", "id": "25"}, {"y": "2244.0232", "x": "518.00775", "id": "26"}, {"y": "5904.534", "x": "1708.055", "id": "27"}, {"y": "4763.474", "x": "1195.0016", "id": "20"}, {"y": "5658.3174", "x": "1490.4585", "id": "21"}, {"y": "5910.0", "x": "2090.0", "id": "22"}, {"y": "10428.612", "x": "1976.1453", "id": "23"}, {"y": "4020.519", "x": "473.6088", "id": "28"}, {"y": "4132.239", "x": "656.0685", "id": "29"}, {"y": "9308.91", "x": "2078.9097", "id": "407"}, {"y": "6114.444", "x": "1752.4427", "id": "406"}, {"y": "6408.394", "x": "1771.3534", "id": "405"}, {"y": "5883.2383", "x": "1350.1763", "id": "404"}, {"y": "1870.0", "x": "820.0", "id": "403"}, {"y": "1771.4519", "x": "866.33655", "id": "402"}, {"y": "4251.844", "x": "910.6515", "id": "401"}, {"y": "5701.44", "x": "1547.667", "id": "400"}, {"y": "3820.0", "x": "920.0", "id": "409"}, {"y": "8470.0", "x": "1980.0", "id": "408"}, {"y": "5811.0215", "x": "1457.3181", "id": "379"}, {"y": "7561.9917", "x": "1149.6216", "id": "378"}, {"y": "5190.0", "x": "900.0", "id": "371"}, {"y": "9823.822", "x": "1961.2355", "id": "370"}, {"y": "3350.0", "x": "1460.0", "id": "373"}, {"y": "6320.589", "x": "2068.5894", "id": "372"}, {"y": "6440.5493", "x": "1223.8052", "id": "375"}, {"y": "5978.3237", "x": "1844.9374", "id": "374"}, {"y": "9966.974", "x": "1767.5333", "id": "377"}, {"y": "3179.7285", "x": "1260.2719", "id": "376"}, {"y": "5903.054", "x": "1800.4238", "id": "393"}, {"y": "1850.0", "x": "900.0", "id": "392"}, {"y": "4282.389", "x": "692.1925", "id": "88"}, {"y": "7924.365", "x": "1631.2698", "id": "89"}, {"y": "4225.035", "x": "992.3115", "id": "397"}, {"y": "8254.186", "x": "1572.1819", "id": "396"}, {"y": "1810.0", "x": "1010.0", "id": "395"}, {"y": "6016.0737", "x": "1786.7819", "id": "394"}, {"y": "6581.807", "x": "1653.3843", "id": "82"}, {"y": "1560.0", "x": "580.0", "id": "83"}, {"y": "5867.262", "x": "1265.8097", "id": "80"}, {"y": "3841.7932", "x": "1341.4723", "id": "398"}, {"y": "8704.607", "x": "1590.9465", "id": "86"}, {"y": "5901.0728", "x": "1875.7727", "id": "87"}, {"y": "10452.305", "x": "1905.8098", "id": "84"}, {"y": "8105.4023", "x": "1313.2413", "id": "85"}, {"y": "5827.9873", "x": "1545.6992", "id": "7"}, {"y": "1157.0388", "x": "510.5054", "id": "245"}, {"y": "5709.933", "x": "1699.9027", "id": "244"}, {"y": "10050.0", "x": "1510.0", "id": "247"}, {"y": "4208.5176", "x": "676.61383", "id": "246"}, {"y": "5041.0625", "x": "1245.6195", "id": "241"}, {"y": "5942.0786", "x": "1765.3901", "id": "240"}, {"y": "5906.7114", "x": "1948.2338", "id": "243"}, {"y": "2527.462", "x": "573.616", "id": "242"}, {"y": "5806.6807", "x": "1654.0032", "id": "249"}, {"y": "8905.956", "x": "1453.0361", "id": "248"}, {"y": "10424.0", "x": "2174.0", "id": "179"}, {"y": "992.3004", "x": "397.4487", "id": "178"}, {"y": "2460.0", "x": "1010.0", "id": "177"}, {"y": "3864.9097", "x": "875.5588", "id": "176"}, {"y": "5281.9976", "x": "1437.6273", "id": "175"}, {"y": "1844.1222", "x": "584.7023", "id": "174"}, {"y": "5972.084", "x": "1984.3956", "id": "173"}, {"y": "172.74677", "x": "443.24866", "id": "172"}, {"y": "5559.404", "x": "1572.6665", "id": "171"}, {"y": "2980.0", "x": "840.0", "id": "170"}, {"y": "4384.696", "x": "646.8303", "id": "182"}, {"y": "350.0", "x": "440.0", "id": "183"}, {"y": "5341.824", "x": "1320.0139", "id": "180"}, {"y": "6665.4688", "x": "1671.6749", "id": "2"}, {"y": "10120.0", "x": "1940.0", "id": "186"}, {"y": "8370.0", "x": "1700.0", "id": "187"}, {"y": "3906.819", "x": "334.15414", "id": "184"}, {"y": "4011.7366", "x": "542.5085", "id": "185"}, {"y": "9201.793", "x": "1482.4717", "id": "188"}, {"y": "4058.9265", "x": "631.467", "id": "189"}, {"y": "9886.178", "x": "1948.7645", "id": "11"}, {"y": "4839.935", "x": "1375.4302", "id": "10"}, {"y": "3796.7292", "x": "266.19412", "id": "13"}, {"y": "5601.2974", "x": "1516.2717", "id": "12"}, {"y": "2900.0", "x": "700.0", "id": "15"}, {"y": "6845.3477", "x": "1398.252", "id": "14"}, {"y": "5863.3833", "x": "1603.8772", "id": "17"}, {"y": "2640.0", "x": "1050.0", "id": "16"}, {"y": "6279.221", "x": "1411.9658", "id": "19"}, {"y": "3114.88", "x": "938.83997", "id": "18"}, {"y": "3805.4045", "x": "412.74823", "id": "62"}, {"y": "5645.026", "x": "1815.0204", "id": "322"}, {"y": "5562.885", "x": "1256.9735", "id": "323"}, {"y": "9030.0", "x": "1460.0", "id": "320"}, {"y": "6694.3447", "x": "1973.3634", "id": "321"}, {"y": "6030.711", "x": "1708.1666", "id": "326"}, {"y": "6302.2075", "x": "1715.7036", "id": "327"}, {"y": "4332.3745", "x": "620.7791", "id": "324"}, {"y": "5601.9043", "x": "1649.5836", "id": "325"}, {"y": "3599.7285", "x": "260.27176", "id": "328"}, {"y": "6198.9893", "x": "1653.6791", "id": "329"}, {"y": "4940.7", "x": "1410.0", "id": "201"}, {"y": "6128.9253", "x": "1645.045", "id": "200"}, {"y": "6331.6836", "x": "1235.8375", "id": "203"}, {"y": "6821.46", "x": "1228.3127", "id": "202"}, {"y": "5971.54", "x": "1686.024", "id": "205"}, {"y": "5062.6465", "x": "1328.7369", "id": "204"}, {"y": "5084.595", "x": "1164.8685", "id": "207"}, {"y": "3680.0", "x": "410.0", "id": "206"}, {"y": "3979.7383", "x": "406.52744", "id": "209"}, {"y": "7480.0", "x": "1280.0", "id": "208"}, {"y": "600.0", "x": "260.0", "id": "77"}, {"y": "6863.4414", "x": "1292.997", "id": "76"}, {"y": "9187.53", "x": "1385.4711", "id": "75"}, {"y": "5962.447", "x": "1365.274", "id": "74"}, {"y": "2970.0", "x": "730.0", "id": "73"}, {"y": "10079.5205", "x": "1717.5758", "id": "72"}, {"y": "8407.877", "x": "1339.8534", "id": "71"}, {"y": "5339.676", "x": "1398.3618", "id": "70"}, {"y": "9180.844", "x": "1325.4813", "id": "79"}, {"y": "5360.8164", "x": "1049.1765", "id": "78"}, {"y": "1101.789", "x": "464.7854", "id": "8"}, {"y": "5413.8745", "x": "1535.6959", "id": "68"}, {"y": "6222.0024", "x": "1736.1724", "id": "120"}, {"y": "5514.7124", "x": "1633.8749", "id": "121"}, {"y": "3979.9944", "x": "1034.8319", "id": "122"}, {"y": "6174.758", "x": "1213.8352", "id": "123"}, {"y": "6387.708", "x": "1695.9572", "id": "124"}, {"y": "6213.7324", "x": "1865.6354", "id": "125"}, {"y": "9920.0", "x": "2030.0", "id": "126"}, {"y": "6686.598", "x": "1223.3163", "id": "127"}, {"y": "6633.9155", "x": "1268.5476", "id": "128"}, {"y": "6162.225", "x": "1289.5482", "id": "129"}, {"y": "3856.6697", "x": "676.29785", "id": "414"}, {"y": "4127.3145", "x": "901.24524", "id": "415"}, {"y": "730.0", "x": "240.0", "id": "416"}, {"y": "6614.895", "x": "1355.0016", "id": "417"}, {"y": "8773.36", "x": "1553.4454", "id": "410"}, {"y": "4238.579", "x": "386.71606", "id": "411"}, {"y": "3950.0", "x": "1160.0", "id": "412"}, {"y": "3910.8208", "x": "416.76892", "id": "413"}, {"y": "4836.5024", "x": "1468.3633", "id": "418"}, {"y": "7260.0", "x": "1370.0", "id": "419"}, {"y": "3270.0", "x": "950.0", "id": "319"}, {"y": "3620.0", "x": "840.0", "id": "318"}, {"y": "6573.232", "x": "1296.859", "id": "313"}, {"y": "7143.815", "x": "1371.4054", "id": "312"}, {"y": "6095.0347", "x": "1555.1309", "id": "311"}, {"y": "4100.3955", "x": "572.0853", "id": "310"}, {"y": "5103.137", "x": "851.0445", "id": "317"}, {"y": "6756.2173", "x": "1434.7745", "id": "316"}, {"y": "5607.4585", "x": "1733.5127", "id": "315"}, {"y": "3815.6023", "x": "546.5492", "id": "314"}, {"y": "3600.0", "x": "390.0", "id": "3"}, {"y": "10480.77", "x": "1836.9048", "id": "368"}, {"y": "5805.0806", "x": "1216.0645", "id": "369"}, {"y": "6068.357", "x": "1629.849", "id": "366"}, {"y": "3738.0215", "x": "924.2633", "id": "367"}, {"y": "9320.0", "x": "1990.0", "id": "364"}, {"y": "2390.6763", "x": "569.1177", "id": "365"}, {"y": "2550.0", "x": "870.0", "id": "362"}, {"y": "7470.012", "x": "1143.6074", "id": "363"}, {"y": "3020.0", "x": "770.0", "id": "360"}, {"y": "6811.335", "x": "1528.0306", "id": "361"}, {"y": "9730.0", "x": "1890.0", "id": "380"}, {"y": "4054.2764", "x": "396.68582", "id": "381"}, {"y": "3761.9253", "x": "1285.3859", "id": "382"}, {"y": "6597.1924", "x": "1732.825", "id": "383"}, {"y": "8202.034", "x": "1536.7517", "id": "384"}, {"y": "6258.7056", "x": "1811.239", "id": "385"}, {"y": "5743.6113", "x": "1617.8342", "id": "386"}, {"y": "3988.548", "x": "1313.6635", "id": "387"}, {"y": "1820.0", "x": "510.0", "id": "388"}, {"y": "5792.638", "x": "1822.9191", "id": "389"}, {"y": "5559.745", "x": "1698.6375", "id": "60"}, {"y": "6183.903", "x": "1804.887", "id": "61"}, {"y": "10580.0", "x": "1930.0", "id": "258"}, {"y": "6133.203", "x": "1517.1184", "id": "259"}, {"y": "4905.9165", "x": "1777.5095", "id": "64"}, {"y": "5627.343", "x": "1581.2734", "id": "65"}, {"y": "5280.0", "x": "1200.0", "id": "66"}, {"y": "4030.0", "x": "1420.0", "id": "67"}, {"y": "6322.392", "x": "1986.6222", "id": "252"}, {"y": "8138.666", "x": "1552.5568", "id": "69"}, {"y": "3710.0", "x": "1350.0", "id": "250"}, {"y": "9261.09", "x": "2031.0906", "id": "251"}, {"y": "5198.201", "x": "1193.3611", "id": "256"}, {"y": "5670.7856", "x": "1629.4097", "id": "257"}, {"y": "1280.0", "x": "690.0", "id": "254"}, {"y": "8510.0", "x": "1370.0", "id": "255"}, {"y": "580.0", "x": "440.0", "id": "168"}, {"y": "6176.3525", "x": "2028.2388", "id": "169"}, {"y": "9793.981", "x": "1818.6008", "id": "164"}, {"y": "5070.9766", "x": "1642.4744", "id": "165"}, {"y": "3967.4814", "x": "875.37225", "id": "166"}, {"y": "182.73792", "x": "354.89035", "id": "167"}, {"y": "6223.502", "x": "1967.7683", "id": "160"}, {"y": "6693.0337", "x": "1301.1119", "id": "161"}, {"y": "6549.8384", "x": "1899.3914", "id": "162"}, {"y": "10150.0", "x": "2360.0", "id": "163"}, {"y": "6525.5303", "x": "1763.0933", "id": "9"}, {"y": "4771.6187", "x": "1078.9111", "id": "357"}, {"y": "4194.6426", "x": "871.6868", "id": "356"}, {"y": "3465.8096", "x": "1397.2621", "id": "355"}, {"y": "7293.197", "x": "1235.9557", "id": "354"}, {"y": "4304.055", "x": "422.6061", "id": "353"}, {"y": "9912.887", "x": "1808.7378", "id": "352"}, {"y": "6580.3916", "x": "1808.0322", "id": "351"}, {"y": "6122.0005", "x": "1345.1028", "id": "350"}, {"y": "1223.4105", "x": "503.71362", "id": "359"}, {"y": "4249.894", "x": "619.94885", "id": "358"}, {"y": "5030.0", "x": "1530.0", "id": "216"}, {"y": "7640.0", "x": "1540.0", "id": "217"}, {"y": "5894.1226", "x": "1484.9509", "id": "214"}, {"y": "3769.3967", "x": "481.27457", "id": "215"}, {"y": "9810.725", "x": "1892.985", "id": "212"}, {"y": "490.0", "x": "370.0", "id": "213"}, {"y": "4168.492", "x": "962.33453", "id": "210"}, {"y": "987.19995", "x": "250.0", "id": "211"}, {"y": "2730.0", "x": "760.0", "id": "218"}, {"y": "4332.7734", "x": "508.12344", "id": "219"}, {"y": "3809.0376", "x": "341.75757", "id": "289"}, {"y": "1250.0", "x": "970.0", "id": "288"}, {"y": "4852.7397", "x": "1703.286", "id": "4"}, {"y": "3689.073", "x": "976.2357", "id": "281"}, {"y": "9886.1045", "x": "1869.0615", "id": "280"}, {"y": "4750.0", "x": "750.0", "id": "283"}, {"y": "8866.243", "x": "1526.9017", "id": "282"}, {"y": "10390.992", "x": "1862.4336", "id": "285"}, {"y": "8244.44", "x": "1422.0933", "id": "284"}, {"y": "8417.93", "x": "1535.9766", "id": "287"}, {"y": "4620.0", "x": "1068.866", "id": "286"}, {"y": "10460.0", "x": "1576.0", "id": "263"}, {"y": "470.0", "x": "250.0", "id": "262"}, {"y": "5273.9077", "x": "1280.9703", "id": "261"}, {"y": "5836.591", "x": "1778.8602", "id": "260"}, {"y": "5657.865", "x": "1420.2837", "id": "267"}, {"y": "6525.184", "x": "1362.0217", "id": "266"}, {"y": "9600.0", "x": "1630.0", "id": "265"}, {"y": "6795.2734", "x": "1346.0133", "id": "264"}, {"y": "4420.0", "x": "980.0", "id": "269"}, {"y": "3266.6367", "x": "753.2727", "id": "268"}, {"y": "8316.471", "x": "1327.6488", "id": "59"}, {"y": "6451.315", "x": "1823.6628", "id": "58"}, {"y": "6299.5566", "x": "1850.7803", "id": "55"}, {"y": "7397.467", "x": "1182.5912", "id": "54"}, {"y": "2290.0", "x": "740.0", "id": "57"}, {"y": "5852.499", "x": "1712.5704", "id": "56"}, {"y": "6522.679", "x": "1203.7257", "id": "51"}, {"y": "6588.1807", "x": "1569.7212", "id": "50"}, {"y": "3774.849", "x": "992.0796", "id": "53"}, {"y": "7950.0", "x": "1440.0", "id": "52"}, {"y": "5481.5815", "x": "1562.2437", "id": "63"}, {"y": "5319.2705", "x": "1110.6534", "id": "115"}, {"y": "6403.594", "x": "1306.1542", "id": "114"}, {"y": "9267.26", "x": "1333.6224", "id": "117"}, {"y": "5117.3267", "x": "1316.6091", "id": "116"}, {"y": "5768.84", "x": "1748.0411", "id": "111"}, {"y": "9865.186", "x": "1739.821", "id": "110"}, {"y": "6067.453", "x": "1838.8214", "id": "113"}, {"y": "5842.4844", "x": "1913.6599", "id": "253"}, {"y": "3974.0974", "x": "623.1026", "id": "119"}, {"y": "3837.7844", "x": "794.69556", "id": "118"}, {"y": "670.0", "x": "170.0", "id": "308"}, {"y": "6096.4346", "x": "1914.7914", "id": "309"}, {"y": "10610.0", "x": "2066.0", "id": "300"}, {"y": "3475.2002", "x": "910.0", "id": "301"}, {"y": "2450.0", "x": "680.0", "id": "302"}, {"y": "9010.0", "x": "1560.0", "id": "303"}, {"y": "3862.8818", "x": "380.1249", "id": "304"}, {"y": "7570.528", "x": "1244.1799", "id": "305"}, {"y": "3049.92", "x": "987.56006", "id": "306"}, {"y": "6747.2617", "x": "1506.5638", "id": "307"}, {"y": "5190.6934", "x": "1273.902", "id": "181"}, {"y": "7350.0", "x": "1730.0", "id": "229"}, {"y": "6500.999", "x": "1284.6204", "id": "228"}, {"y": "2308.8506", "x": "460.49655", "id": "227"}, {"y": "1175.635", "x": "438.73022", "id": "226"}, {"y": "5522.3213", "x": "1494.1693", "id": "225"}, {"y": "7227.158", "x": "1246.7358", "id": "224"}, {"y": "8042.0254", "x": "1275.2152", "id": "223"}, {"y": "5706.856", "x": "1811.5203", "id": "222"}, {"y": "4291.939", "x": "543.0724", "id": "221"}, {"y": "3570.0", "x": "1000.0", "id": "220"}, {"y": "4106.0796", "x": "448.24478", "id": "391"}, {"y": "1168.2875", "x": "581.8372", "id": "390"}, {"y": "6331.398", "x": "1787.2991", "id": "151"}, {"y": "6153.854", "x": "1923.716", "id": "150"}, {"y": "7320.0", "x": "1440.0", "id": "153"}, {"y": "6584.253", "x": "1428.4275", "id": "152"}, {"y": "3920.2104", "x": "827.2061", "id": "155"}, {"y": "6518.8877", "x": "1599.9932", "id": "154"}, {"y": "9080.0", "x": "1530.0", "id": "157"}, {"y": "7700.0", "x": "1500.0", "id": "156"}, {"y": "7900.0", "x": "1730.0", "id": "159"}, {"y": "6359.846", "x": "1437.2743", "id": "158"}, {"y": "6060.0", "x": "1370.0", "id": "112"}, {"y": "3392.7998", "x": "910.0", "id": "399"}, {"y": "6970.0", "x": "1480.0", "id": "81"}, {"y": "5952.965", "x": "1910.2065", "id": "48"}, {"y": "5732.8545", "x": "1478.922", "id": "49"}, {"y": "904.80005", "x": "250.0", "id": "46"}, {"y": "2400.0", "x": "490.0", "id": "47"}, {"y": "5310.2715", "x": "1000.27167", "id": "44"}, {"y": "5409.491", "x": "1344.2308", "id": "45"}, {"y": "1037.7693", "x": "448.54013", "id": "42"}, {"y": "6465.2227", "x": "1741.9225", "id": "43"}, {"y": "7958.3184", "x": "1563.3638", "id": "40"}, {"y": "6970.0", "x": "1330.0", "id": "41"}, {"y": "7780.0", "x": "1441.3999", "id": "5"}
],
  "links": [{"source": 0, "target": 50}, {"source": 0, "target": 57}, {"source": 0, "target": 312}, {"source": 0, "target": 145}, {"source": 0, "target": 163}, {"source": 0, "target": 34}, {"source": 0, "target": 16}, {"source": 0, "target": 9}, {"source": 0, "target": 392}, {"source": 0, "target": 320}, {"source": 1, "target": 336}, {"source": 2, "target": 188}, {"source": 3, "target": 144}, {"source": 3, "target": 87}, {"source": 3, "target": 89}, {"source": 4, "target": 204}, {"source": 5, "target": 50}, {"source": 5, "target": 95}, {"source": 5, "target": 248}, {"source": 6, "target": 305}, {"source": 7, "target": 209}, {"source": 8, "target": 17}, {"source": 9, "target": 189}, {"source": 9, "target": 16}, {"source": 9, "target": 187}, {"source": 10, "target": 256}, {"source": 10, "target": 220}, {"source": 10, "target": 389}, {"source": 10, "target": 195}, {"source": 10, "target": 252}, {"source": 11, "target": 224}, {"source": 11, "target": 17}, {"source": 11, "target": 265}, {"source": 12, "target": 259}, {"source": 13, "target": 31}, {"source": 13, "target": 188}, {"source": 14, "target": 337}, {"source": 14, "target": 29}, {"source": 14, "target": 203}, {"source": 14, "target": 188}, {"source": 14, "target": 102}, {"source": 14, "target": 169}, {"source": 14, "target": 90}, {"source": 14, "target": 299}, {"source": 15, "target": 74}, {"source": 15, "target": 204}, {"source": 16, "target": 219}, {"source": 16, "target": 243}, {"source": 16, "target": 250}, {"source": 16, "target": 379}, {"source": 16, "target": 262}, {"source": 16, "target": 92}, {"source": 16, "target": 200}, {"source": 16, "target": 187}, {"source": 16, "target": 76}, {"source": 17, "target": 48}, {"source": 18, "target": 373}, {"source": 18, "target": 245}, {"source": 18, "target": 328}, {"source": 19, "target": 99}, {"source": 19, "target": 318}, {"source": 20, "target": 292}, {"source": 20, "target": 238}, {"source": 20, "target": 279}, {"source": 21, "target": 388}, {"source": 21, "target": 48}, {"source": 22, "target": 340}, {"source": 22, "target": 102}, {"source": 23, "target": 251}, {"source": 24, "target": 173}, {"source": 24, "target": 57}, {"source": 25, "target": 85}, {"source": 25, "target": 116}, {"source": 25, "target": 357}, {"source": 26, "target": 44}, {"source": 26, "target": 98}, {"source": 27, "target": 368}, {"source": 28, "target": 44}, {"source": 28, "target": 40}, {"source": 28, "target": 301}, {"source": 29, "target": 102}, {"source": 29, "target": 203}, {"source": 29, "target": 188}, {"source": 29, "target": 337}, {"source": 29, "target": 169}, {"source": 29, "target": 90}, {"source": 29, "target": 299}, {"source": 30, "target": 94}, {"source": 30, "target": 344}, {"source": 30, "target": 290}, {"source": 31, "target": 65}, {"source": 32, "target": 142}, {"source": 33, "target": 151}, {"source": 35, "target": 362}, {"source": 35, "target": 67}, {"source": 36, "target": 289}, {"source": 36, "target": 261}, {"source": 36, "target": 130}, {"source": 37, "target": 397}, {"source": 37, "target": 119}, {"source": 37, "target": 176}, {"source": 37, "target": 124}, {"source": 37, "target": 40}, {"source": 37, "target": 138}, {"source": 37, "target": 306}, {"source": 37, "target": 49}, {"source": 38, "target": 192}, {"source": 38, "target": 324}, {"source": 38, "target": 186}, {"source": 38, "target": 262}, {"source": 39, "target": 356}, {"source": 39, "target": 66}, {"source": 40, "target": 397}, {"source": 40, "target": 176}, {"source": 40, "target": 124}, {"source": 40, "target": 206}, {"source": 40, "target": 138}, {"source": 40, "target": 306}, {"source": 40, "target": 49}, {"source": 41, "target": 52}, {"source": 41, "target": 152}, {"source": 42, "target": 385}, {"source": 43, "target": 370}, {"source": 43, "target": 391}, {"source": 44, "target": 399}, {"source": 44, "target": 195}, {"source": 44, "target": 124}, {"source": 44, "target": 237}, {"source": 44, "target": 74}, {"source": 44, "target": 111}, {"source": 44, "target": 308}, {"source": 45, "target": 303}, {"source": 45, "target": 344}, {"source": 45, "target": 288}, {"source": 45, "target": 333}, {"source": 46, "target": 372}, {"source": 46, "target": 131}, {"source": 46, "target": 57}, {"source": 47, "target": 400}, {"source": 48, "target": 202}, {"source": 48, "target": 265}, {"source": 49, "target": 397}, {"source": 49, "target": 176}, {"source": 49, "target": 124}, {"source": 49, "target": 138}, {"source": 49, "target": 306}, {"source": 50, "target": 258}, {"source": 50, "target": 315}, {"source": 50, "target": 80}, {"source": 51, "target": 162}, {"source": 51, "target": 226}, {"source": 51, "target": 141}, {"source": 52, "target": 386}, {"source": 52, "target": 231}, {"source": 52, "target": 298}, {"source": 52, "target": 319}, {"source": 53, "target": 57}, {"source": 54, "target": 151}, {"source": 54, "target": 260}, {"source": 54, "target": 347}, {"source": 55, "target": 57}, {"source": 56, "target": 77}, {"source": 56, "target": 96}, {"source": 57, "target": 400}, {"source": 57, "target": 258}, {"source": 57, "target": 106}, {"source": 57, "target": 147}, {"source": 57, "target": 111}, {"source": 57, "target": 154}, {"source": 57, "target": 92}, {"source": 57, "target": 267}, {"source": 57, "target": 131}, {"source": 57, "target": 97}, {"source": 57, "target": 101}, {"source": 57, "target": 344}, {"source": 57, "target": 281}, {"source": 57, "target": 393}, {"source": 57, "target": 244}, {"source": 57, "target": 313}, {"source": 57, "target": 249}, {"source": 57, "target": 82}, {"source": 58, "target": 419}, {"source": 59, "target": 270}, {"source": 59, "target": 329}, {"source": 59, "target": 179}, {"source": 60, "target": 259}, {"source": 61, "target": 133}, {"source": 61, "target": 280}, {"source": 62, "target": 63}, {"source": 62, "target": 213}, {"source": 62, "target": 236}, {"source": 62, "target": 358}, {"source": 63, "target": 213}, {"source": 63, "target": 198}, {"source": 63, "target": 405}, {"source": 63, "target": 69}, {"source": 63, "target": 236}, {"source": 64, "target": 188}, {"source": 64, "target": 368}, {"source": 64, "target": 348}, {"source": 66, "target": 115}, {"source": 66, "target": 412}, {"source": 66, "target": 377}, {"source": 66, "target": 101}, {"source": 66, "target": 386}, {"source": 66, "target": 175}, {"source": 66, "target": 356}, {"source": 66, "target": 298}, {"source": 68, "target": 328}, {"source": 68, "target": 171}, {"source": 70, "target": 74}, {"source": 71, "target": 351}, {"source": 72, "target": 267}, {"source": 73, "target": 180}, {"source": 74, "target": 204}, {"source": 74, "target": 151}, {"source": 74, "target": 308}, {"source": 75, "target": 94}, {"source": 77, "target": 386}, {"source": 77, "target": 87}, {"source": 78, "target": 255}, {"source": 78, "target": 349}, {"source": 79, "target": 103}, {"source": 79, "target": 224}, {"source": 80, "target": 394}, {"source": 81, "target": 363}, {"source": 82, "target": 137}, {"source": 83, "target": 322}, {"source": 83, "target": 398}, {"source": 83, "target": 389}, {"source": 83, "target": 361}, {"source": 84, "target": 117}, {"source": 84, "target": 259}, {"source": 84, "target": 217}, {"source": 85, "target": 266}, {"source": 85, "target": 215}, {"source": 86, "target": 255}, {"source": 87, "target": 175}, {"source": 87, "target": 89}, {"source": 88, "target": 374}, {"source": 88, "target": 176}, {"source": 88, "target": 409}, {"source": 88, "target": 369}, {"source": 90, "target": 337}, {"source": 90, "target": 203}, {"source": 90, "target": 188}, {"source": 90, "target": 102}, {"source": 90, "target": 169}, {"source": 90, "target": 299}, {"source": 91, "target": 276}, {"source": 91, "target": 249}, {"source": 92, "target": 219}, {"source": 92, "target": 258}, {"source": 93, "target": 321}, {"source": 93, "target": 111}, {"source": 94, "target": 217}, {"source": 94, "target": 344}, {"source": 94, "target": 383}, {"source": 94, "target": 366}, {"source": 94, "target": 290}, {"source": 96, "target": 356}, {"source": 97, "target": 235}, {"source": 98, "target": 138}, {"source": 99, "target": 406}, {"source": 99, "target": 287}, {"source": 99, "target": 206}, {"source": 99, "target": 318}, {"source": 99, "target": 265}, {"source": 99, "target": 224}, {"source": 100, "target": 131}, {"source": 101, "target": 377}, {"source": 101, "target": 179}, {"source": 102, "target": 169}, {"source": 102, "target": 352}, {"source": 102, "target": 185}, {"source": 102, "target": 203}, {"source": 102, "target": 361}, {"source": 102, "target": 105}, {"source": 102, "target": 247}, {"source": 102, "target": 227}, {"source": 102, "target": 188}, {"source": 102, "target": 337}, {"source": 102, "target": 390}, {"source": 102, "target": 339}, {"source": 102, "target": 299}, {"source": 103, "target": 323}, {"source": 104, "target": 407}, {"source": 104, "target": 254}, {"source": 104, "target": 107}, {"source": 108, "target": 368}, {"source": 109, "target": 240}, {"source": 110, "target": 269}, {"source": 111, "target": 321}, {"source": 111, "target": 117}, {"source": 111, "target": 124}, {"source": 111, "target": 344}, {"source": 112, "target": 180}, {"source": 113, "target": 273}, {"source": 114, "target": 152}, {"source": 114, "target": 175}, {"source": 117, "target": 311}, {"source": 117, "target": 341}, {"source": 118, "target": 289}, {"source": 120, "target": 157}, {"source": 121, "target": 275}, {"source": 122, "target": 163}, {"source": 123, "target": 188}, {"source": 124, "target": 397}, {"source": 124, "target": 168}, {"source": 124, "target": 212}, {"source": 124, "target": 176}, {"source": 124, "target": 165}, {"source": 124, "target": 391}, {"source": 124, "target": 233}, {"source": 124, "target": 362}, {"source": 124, "target": 301}, {"source": 124, "target": 292}, {"source": 124, "target": 206}, {"source": 124, "target": 138}, {"source": 124, "target": 306}, {"source": 125, "target": 396}, {"source": 125, "target": 279}, {"source": 126, "target": 153}, {"source": 127, "target": 144}, {"source": 127, "target": 175}, {"source": 127, "target": 128}, {"source": 127, "target": 149}, {"source": 129, "target": 147}, {"source": 130, "target": 297}, {"source": 132, "target": 185}, {"source": 134, "target": 220}, {"source": 134, "target": 380}, {"source": 135, "target": 259}, {"source": 136, "target": 325}, {"source": 138, "target": 397}, {"source": 138, "target": 176}, {"source": 138, "target": 301}, {"source": 138, "target": 306}, {"source": 139, "target": 358}, {"source": 140, "target": 205}, {"source": 140, "target": 369}, {"source": 140, "target": 150}, {"source": 141, "target": 368}, {"source": 142, "target": 253}, {"source": 143, "target": 211}, {"source": 143, "target": 165}, {"source": 143, "target": 156}, {"source": 143, "target": 166}, {"source": 143, "target": 391}, {"source": 145, "target": 180}, {"source": 145, "target": 320}, {"source": 146, "target": 417}, {"source": 147, "target": 350}, {"source": 147, "target": 327}, {"source": 148, "target": 339}, {"source": 151, "target": 401}, {"source": 151, "target": 277}, {"source": 151, "target": 416}, {"source": 151, "target": 359}, {"source": 151, "target": 183}, {"source": 151, "target": 347}, {"source": 151, "target": 310}, {"source": 151, "target": 204}, {"source": 153, "target": 224}, {"source": 153, "target": 265}, {"source": 155, "target": 247}, {"source": 157, "target": 264}, {"source": 157, "target": 375}, {"source": 157, "target": 342}, {"source": 157, "target": 286}, {"source": 157, "target": 184}, {"source": 157, "target": 170}, {"source": 157, "target": 338}, {"source": 158, "target": 390}, {"source": 159, "target": 168}, {"source": 160, "target": 387}, {"source": 160, "target": 319}, {"source": 160, "target": 231}, {"source": 161, "target": 168}, {"source": 161, "target": 289}, {"source": 162, "target": 226}, {"source": 163, "target": 248}, {"source": 163, "target": 207}, {"source": 163, "target": 392}, {"source": 163, "target": 320}, {"source": 164, "target": 383}, {"source": 164, "target": 217}, {"source": 166, "target": 283}, {"source": 167, "target": 377}, {"source": 168, "target": 196}, {"source": 168, "target": 362}, {"source": 168, "target": 367}, {"source": 168, "target": 289}, {"source": 168, "target": 266}, {"source": 168, "target": 391}, {"source": 169, "target": 337}, {"source": 169, "target": 203}, {"source": 169, "target": 188}, {"source": 169, "target": 299}, {"source": 170, "target": 375}, {"source": 171, "target": 415}, {"source": 172, "target": 356}, {"source": 172, "target": 270}, {"source": 174, "target": 228}, {"source": 175, "target": 282}, {"source": 175, "target": 298}, {"source": 176, "target": 397}, {"source": 176, "target": 306}, {"source": 177, "target": 305}, {"source": 178, "target": 234}, {"source": 179, "target": 253}, {"source": 179, "target": 199}, {"source": 179, "target": 225}, {"source": 179, "target": 272}, {"source": 179, "target": 393}, {"source": 181, "target": 343}, {"source": 181, "target": 305}, {"source": 181, "target": 326}, {"source": 182, "target": 362}, {"source": 182, "target": 344}, {"source": 182, "target": 414}, {"source": 184, "target": 368}, {"source": 184, "target": 309}, {"source": 186, "target": 331}, {"source": 187, "target": 371}, {"source": 188, "target": 337}, {"source": 188, "target": 295}, {"source": 188, "target": 348}, {"source": 188, "target": 223}, {"source": 188, "target": 203}, {"source": 188, "target": 247}, {"source": 188, "target": 368}, {"source": 188, "target": 365}, {"source": 188, "target": 268}, {"source": 188, "target": 229}, {"source": 188, "target": 299}, {"source": 190, "target": 325}, {"source": 191, "target": 211}, {"source": 193, "target": 284}, {"source": 193, "target": 234}, {"source": 193, "target": 346}, {"source": 194, "target": 225}, {"source": 195, "target": 222}, {"source": 195, "target": 399}, {"source": 197, "target": 270}, {"source": 199, "target": 253}, {"source": 199, "target": 381}, {"source": 201, "target": 391}, {"source": 203, "target": 402}, {"source": 203, "target": 337}, {"source": 203, "target": 299}, {"source": 204, "target": 277}, {"source": 206, "target": 396}, {"source": 206, "target": 416}, {"source": 206, "target": 233}, {"source": 206, "target": 237}, {"source": 208, "target": 284}, {"source": 208, "target": 261}, {"source": 209, "target": 263}, {"source": 210, "target": 212}, {"source": 211, "target": 251}, {"source": 211, "target": 216}, {"source": 212, "target": 266}, {"source": 212, "target": 238}, {"source": 213, "target": 236}, {"source": 214, "target": 349}, {"source": 217, "target": 296}, {"source": 218, "target": 263}, {"source": 218, "target": 324}, {"source": 220, "target": 390}, {"source": 220, "target": 271}, {"source": 221, "target": 373}, {"source": 221, "target": 343}, {"source": 221, "target": 300}, {"source": 224, "target": 406}, {"source": 224, "target": 265}, {"source": 225, "target": 272}, {"source": 228, "target": 232}, {"source": 228, "target": 344}, {"source": 229, "target": 365}, {"source": 230, "target": 413}, {"source": 231, "target": 415}, {"source": 232, "target": 234}, {"source": 233, "target": 238}, {"source": 234, "target": 284}, {"source": 234, "target": 362}, {"source": 234, "target": 388}, {"source": 236, "target": 242}, {"source": 238, "target": 285}, {"source": 239, "target": 368}, {"source": 240, "target": 241}, {"source": 240, "target": 385}, {"source": 240, "target": 349}, {"source": 241, "target": 307}, {"source": 242, "target": 318}, {"source": 246, "target": 255}, {"source": 253, "target": 407}, {"source": 253, "target": 351}, {"source": 254, "target": 267}, {"source": 255, "target": 358}, {"source": 255, "target": 399}, {"source": 257, "target": 266}, {"source": 257, "target": 287}, {"source": 258, "target": 275}, {"source": 260, "target": 382}, {"source": 261, "target": 284}, {"source": 267, "target": 360}, {"source": 267, "target": 313}, {"source": 267, "target": 334}, {"source": 269, "target": 412}, {"source": 270, "target": 329}, {"source": 271, "target": 355}, {"source": 273, "target": 277}, {"source": 274, "target": 302}, {"source": 276, "target": 294}, {"source": 278, "target": 339}, {"source": 280, "target": 289}, {"source": 281, "target": 313}, {"source": 281, "target": 291}, {"source": 283, "target": 370}, {"source": 283, "target": 345}, {"source": 283, "target": 391}, {"source": 290, "target": 363}, {"source": 290, "target": 344}, {"source": 292, "target": 306}, {"source": 292, "target": 301}, {"source": 293, "target": 339}, {"source": 297, "target": 410}, {"source": 298, "target": 332}, {"source": 299, "target": 337}, {"source": 302, "target": 368}, {"source": 303, "target": 344}, {"source": 304, "target": 400}, {"source": 305, "target": 343}, {"source": 305, "target": 326}, {"source": 306, "target": 397}, {"source": 310, "target": 317}, {"source": 314, "target": 389}, {"source": 316, "target": 368}, {"source": 319, "target": 395}, {"source": 320, "target": 330}, {"source": 322, "target": 403}, {"source": 322, "target": 419}, {"source": 322, "target": 361}, {"source": 325, "target": 368}, {"source": 326, "target": 343}, {"source": 328, "target": 411}, {"source": 335, "target": 368}, {"source": 336, "target": 341}, {"source": 339, "target": 361}, {"source": 341, "target": 350}, {"source": 344, "target": 362}, {"source": 347, "target": 385}, {"source": 347, "target": 399}, {"source": 347, "target": 349}, {"source": 348, "target": 368}, {"source": 353, "target": 416}, {"source": 354, "target": 396}, {"source": 358, "target": 364}, {"source": 358, "target": 385}, {"source": 361, "target": 403}, {"source": 361, "target": 404}, {"source": 361, "target": 417}, {"source": 361, "target": 419}, {"source": 363, "target": 413}, {"source": 376, "target": 407}, {"source": 378, "target": 402}, {"source": 384, "target": 399}, {"source": 389, "target": 418}, {"source": 399, "target": 418}, {"source": 403, "target": 419}, {"source": 404, "target": 417}, {"source": 408, "target": 418}], "multigraph": false}